nomnomdata/cli/__init__.py
nomnomdata/cli/cli.py
nomnomdata/cli/tests/__init__.py
nomnomdata/cli/tests/test_cli.py
nomnomdata_cli-2.0.1.dist-info/LICENSE
nomnomdata_cli-2.0.1.dist-info/METADATA
nomnomdata_cli-2.0.1.dist-info/WHEEL
nomnomdata_cli-2.0.1.dist-info/entry_points.txt
nomnomdata_cli-2.0.1.dist-info/RECORD
